itss1/__init__.py
itss1/fun1.py
itss1/fun2.py
itss1-0.1.dist-info/LICENCE.txt
itss1-0.1.dist-info/METADATA
itss1-0.1.dist-info/WHEEL
itss1-0.1.dist-info/top_level.txt
itss1-0.1.dist-info/RECORD
